build/lib/build/lib/build/lib/build/lib/build/lib/build/lib/build/lib/build/lib/gqcms/BondOrderOperator.py
build/lib/build/lib/build/lib/build/lib/build/lib/build/lib/build/lib/build/lib/gqcms/ConfigurationInteraction.py
build/lib/build/lib/build/lib/build/lib/build/lib/build/lib/build/lib/build/lib/gqcms/ConstrainedMethod.py
build/lib/build/lib/build/lib/build/lib/build/lib/build/lib/build/lib/build/lib/gqcms/DMRG.py
build/lib/build/lib/build/lib/build/lib/build/lib/build/lib/build/lib/build/lib/gqcms/EDF.py
build/lib/build/lib/build/lib/build/lib/build/lib/build/lib/build/lib/build/lib/gqcms/General.py
build/lib/build/lib/build/lib/build/lib/build/lib/build/lib/build/lib/build/lib/gqcms/HartreeFock.py
build/lib/build/lib/build/lib/build/lib/build/lib/build/lib/build/lib/build/lib/gqcms/Heisenberg.py
build/lib/build/lib/build/lib/build/lib/build/lib/build/lib/build/lib/build/lib/gqcms/Hubbard.py
build/lib/build/lib/build/lib/build/lib/build/lib/build/lib/build/lib/build/lib/gqcms/Information.py
build/lib/build/lib/build/lib/build/lib/build/lib/build/lib/build/lib/build/lib/gqcms/MPD.py
build/lib/build/lib/build/lib/build/lib/build/lib/build/lib/build/lib/build/lib/gqcms/Optimization.py
build/lib/build/lib/build/lib/build/lib/build/lib/build/lib/build/lib/build/lib/gqcms/Scans.py
build/lib/build/lib/build/lib/build/lib/build/lib/build/lib/build/lib/build/lib/gqcms/__init__.py
build/lib/build/lib/build/lib/build/lib/build/lib/build/lib/build/lib/build/lib/gqcms/basis.py
build/lib/build/lib/build/lib/build/lib/build/lib/build/lib/build/lib/build/lib/gqcms/math.py
build/lib/build/lib/build/lib/build/lib/build/lib/build/lib/build/lib/build/lib/gqcms/PlottingTools/LegendPlotter.py
build/lib/build/lib/build/lib/build/lib/build/lib/build/lib/build/lib/build/lib/gqcms/PlottingTools/Plot.py
build/lib/build/lib/build/lib/build/lib/build/lib/build/lib/build/lib/build/lib/gqcms/PlottingTools/__init__.py
GQCMS-0.0.4.dist-info/METADATA
GQCMS-0.0.4.dist-info/WHEEL
GQCMS-0.0.4.dist-info/top_level.txt
GQCMS-0.0.4.dist-info/RECORD
