Metadata-Version: 2.1
Name: GQCMS
Version: 0.0.4
Summary: A computational chemistry package
Home-page: UNKNOWN
Author: ruvdsti and xwieme
License: UNKNOWN
Platform: UNKNOWN
Classifier: Programming Language :: Python :: 3
Requires-Python: >= 3.6
Requires-Dist: numpy (==1.21.0)
Requires-Dist: pandas (==1.5.1)
Requires-Dist: matplotlib (==3.6.2)
Requires-Dist: scipy (==1.9.3)
Requires-Dist: plotly (==5.11.0)
Requires-Dist: seaborn (==0.12.1)
Requires-Dist: nbformat
Requires-Dist: ipython
Requires-Dist: jupyter
